main.v
module pipelined_mips32_processor (
    clk1, clk2
    );
    input clk1, clk2;  //Two clock phases
    reg [31:0] PC;
    //PC = Program Counter

    reg [31:0] IF_ID_IR, IF_ID_NPC;
    //IF_ID_IR = Instruction register in the latch between IR and ID
    //IF_ID_NPC = New Program Counter between IF and ID
    
    reg [31:0] ID_EX_IR, ID_EX_A, ID_EX_B, ID_EX_Imm, ID_EX_NPC;
    //ID_EX_IR = Instruction register in the latch between ID and EX
    //ID_EX_A = stores value of rs
    //ID_EX_B = stores value of rt
    //ID_EX_Imm = Immediate value(sign extended to make it 32 bit)
    //ID_EX_NPC = New Program Counter between ID and EX

    reg [31:0] EX_MEM_IR, EX_MEM_ALUOut, EX_MEM_B;
    reg EX_MEM_BEQ_Cond;
    //EX_MEM_IR = Instruction register in the latchc between EX and MEM
    //EX_MEM_ALUOut = Store Output of Execution(ALU Unit Output)
    //EX_MEM_B = For store operation
    //EX_MEM_BEQ_Cond = Output to BEQ Condition

    reg [31:0] MEM_WB_IR, MEM_WB_ALUOut, MEM_WB_LMD;
    //MEM_WB_IR = Instruction register in the latch between MEM and WB
    //MEM_WB_ALUOut = Contains output of execution
    //MEM_WB_LMD = For load operation

    reg [2:0] ID_EX_TYPE, EX_MEM_TYPE, MEM_WB_TYPE;

    reg[31:0] Reg[0:31]; //32 reigsters of 32 bit
    reg[31:0] Mem[0:1023]; //(32x1024) bits memory = 4Kb memory


    //Opcodes
    parameter
    ADD = 6'b000000,    //rd = rs + rt
    SUB = 6'b000001,    //rd = rs - rt
    MUL = 6'b000010,    //rd = rs * rt
    DIV = 6'b000011,    //rd = rs / rt
    SLT = 6'b000100,    //rd = rs < rt


    AND = 6'b000101,    //rd = rs & rt
    OR  = 6'b000110,    //rd = rs | rt
    SLL = 6'b000111,    //rd = rt << rs
    SRL = 6'b001000,    //rd = rt >> rs

    ADDI = 6'b001001,   //rt = rs + Imm
    SUBI = 6'b001010,   //rt = rs - Imm
    MULI = 6'b001011,   //rt = rs * Imm
    DIVI = 6'b001100,   //rt = rs / Imm
    SLTI = 6'b001101,   //rt = rs < Imm

    BEQ = 6'b001110,    //if(rs==rt) pc+=offset
    
    LW = 6'b010001,     //rt = *(int*)(offset+rs)
    SW = 6'b010010,     //*(int*)(offset+rs) = rt

    HLT = 6'b111111,    //HALT System
    
    //Instruction Type
    RR_ALU = 3'b000,
    RM_ALU = 3'b001,
    LOAD   = 3'b010,
    STORE  = 3'b011,
    BRANCH = 3'b100,
    HALT   = 3'b111;

    reg HALTED;         //if(HLT detected) HALTED=1

    reg TAKEN_BRANCH;   //if(BRANCH detected) TAKEN_BRANCH=l

    //IF Stage
    always @(posedge clk1)
    begin
        if(HALTED==0)
        begin
            if(EX_MEM_IR[31:26]==BEQ && EX_MEM_BEQ_Cond==1)
            begin
                IF_ID_IR <= #2 Mem[EX_MEM_ALUOut];
                IF_ID_NPC <= #2 EX_MEM_ALUOut + 1;
                PC <= #2 EX_MEM_ALUOut + 1;            //Inccreasing program counter by one
                TAKEN_BRANCH <= #2 1'b1;
            end
            else
            begin
                IF_ID_IR <= #2 Mem[PC];
                IF_ID_NPC <= #2 PC + 1;
                PC <= #2 PC + 1;            //Inccreasing program counter by one
            end
        end
    end

    //ID Stage
    always @(posedge clk2)
    begin
        if(HALTED==0)
            begin
                //rs
                if(IF_ID_IR[25:21]==5'b00000)
                    begin
                        ID_EX_A <= 5'b00000;                        
                    end
                else
                    begin
                        ID_EX_A <= #2 Reg[IF_ID_IR[25:21]];
                    end
                //rt
                if(IF_ID_IR[20:16]==5'b00000)
                    begin
                        ID_EX_B <= 5'b00000;
                    end
                else
                    begin
                        ID_EX_B <= #2 Reg[IF_ID_IR[20:16]];
                    end

                case (IF_ID_IR[31:26])
                    ADD, SUB, MUL, DIV, SLT, AND, OR, SLL, SRL: 
                        ID_EX_TYPE <= #2 RR_ALU;
                    ADDI, SUBI, MULI, DIVI, SLTI:
                        ID_EX_TYPE <= #2 RM_ALU;
                    BEQ:
                        ID_EX_TYPE <= #2 BRANCH;
                    LW:
                        ID_EX_TYPE <= #2 LOAD;
                    SW:
                        ID_EX_TYPE <= #2 STORE;
                    HLT:
                        ID_EX_TYPE <= #2 HALT;
                    default:
                        ID_EX_TYPE <= #2 HALT;
                endcase

                ID_EX_IR <= #2 IF_ID_IR;
                ID_EX_NPC <= #2 IF_ID_NPC;
                ID_EX_Imm <= #2 {{16{IF_ID_IR[15]}}, {IF_ID_IR[15:0]}};
            end
    end

    //EX Stage
    always @(posedge clk1)
    begin
        if(HALTED==0)
        begin
            EX_MEM_IR <= #2 ID_EX_IR;
            EX_MEM_TYPE <= #2 ID_EX_TYPE;
            TAKEN_BRANCH <= #2 1'b0;
            case(ID_EX_TYPE)
                RR_ALU:
                    begin
                        case(ID_EX_IR[31:26])
                            ADD:
                                EX_MEM_ALUOut <= #2 ID_EX_A + ID_EX_B;
                            SUB:
                                EX_MEM_ALUOut <= #2 ID_EX_A - ID_EX_B;
                            MUL:
                                EX_MEM_ALUOut <= #2 ID_EX_A * ID_EX_B;
                            DIV:
                                EX_MEM_ALUOut <= #2 ID_EX_A / ID_EX_B;
                            SLT:
                                EX_MEM_ALUOut <= #2 ID_EX_A < ID_EX_B;
                            AND:
                                EX_MEM_ALUOut <= #2 ID_EX_A & ID_EX_B;
                            OR:
                                EX_MEM_ALUOut <= #2 ID_EX_A | ID_EX_B;
                            SLL:
                                EX_MEM_ALUOut <= #2 ID_EX_B << ID_EX_A;
                            SRL:
                                EX_MEM_ALUOut <= #2 ID_EX_B >> ID_EX_A;
                        endcase
                    end
                RM_ALU:
                    begin
                        case(ID_EX_IR[31:26])
                            ADDI:
                                EX_MEM_ALUOut <= #2 ID_EX_A + ID_EX_Imm;
                            SUBI:
                                EX_MEM_ALUOut <= #2 ID_EX_A - ID_EX_Imm;
                            MULI:
                                EX_MEM_ALUOut <= #2 ID_EX_A * ID_EX_Imm;
                            DIVI:
                                EX_MEM_ALUOut <= #2 ID_EX_A / ID_EX_Imm;
                            SLTI:
                                EX_MEM_ALUOut <= #2 ID_EX_A < ID_EX_Imm;
                        endcase
                    end
                BRANCH:
                    begin
                        if(ID_EX_IR[31:26]==BEQ)
                        begin
                            EX_MEM_ALUOut <= #2 ID_EX_NPC + ID_EX_Imm;
                            EX_MEM_BEQ_Cond <= (ID_EX_A == ID_EX_B);
                        end
                    end
                LOAD, STORE:
                    begin
                        EX_MEM_ALUOut <= #2 ID_EX_A + ID_EX_Imm;
                        EX_MEM_B <= #2 ID_EX_B;
                    end
            endcase
        end
    end

    //MEM Stage
    always @(posedge clk2)
    begin
        if(HALTED==0)
        begin
            MEM_WB_TYPE <= #2 EX_MEM_TYPE;
            MEM_WB_IR <= #2 EX_MEM_IR;
            case(EX_MEM_TYPE)
                RR_ALU, RM_ALU:
                    MEM_WB_ALUOut <= #2 EX_MEM_ALUOut;
                LOAD:
                    MEM_WB_LMD <= #2 Mem[EX_MEM_ALUOut];
                STORE:
                begin
                    if(TAKEN_BRANCH == 0)    //Disbale writing
                        begin                            
                            Mem[EX_MEM_ALUOut] <= #2 EX_MEM_B;      //Writing in Memory                                
                        end
                end
            endcase
        end    
    end

    //WB Stage
    always @(posedge clk1)
    begin
        if(TAKEN_BRANCH==0)
        begin
            case(MEM_WB_TYPE)
                RR_ALU:
                    Reg[MEM_WB_IR[15:11]] <= #2 MEM_WB_ALUOut;  //In rd
                RM_ALU:
                    Reg[MEM_WB_IR[20:16]] <= #2 MEM_WB_ALUOut;  //In rt
                LOAD:
                    Reg[MEM_WB_IR[20:16]] <= #2 MEM_WB_LMD;     //In rt
                HALT:
                    HALTED <= #2 1'b1;
            endcase
        end
    end
endmodule

main_tb.v
`timescale 1ns/100ps
`include "main.v"

module mips32_pipelined_tb1;
    reg clk1, clk2;
    integer k;

    pipelined_mips32_processor processor(clk1, clk2);

    initial
    begin
        clk1 = 0; clk2 = 0;
        repeat(20)
        begin
            #5 clk1 = 1;
            #5 clk1 = 0;
            #5 clk2 = 1;
            #5 clk2 = 0;
        end
    end

    initial
    begin
         $dumpfile("main_tb.vcd");
        $dumpvars (0, mips32_pipelined_tb1);

        for(k=0;k<31;k++)
            processor.Reg[k] = 0;
        processor.Mem[0] = 32'h2401000a;    //ADDI R1, R0, 10
        processor.Mem[1] = 32'h24020014;    //ADDI R2, R0, 20
        processor.Mem[2] = 32'h2403001e;    //ADDI R3, R0, 30
        processor.Mem[3] = 32'h18e73800;    //OR R7, R7, R7(Dummy Instruction)
        processor.Mem[4] = 32'h00222000;    //ADD R4, R1, R2
        processor.Mem[5] = 32'h00432800;    //ADD R5, R2, R3
        processor.Mem[6] = 32'h18e73800;    //OR R7, R7, R7(Dummy Instruction)
        processor.Mem[7] = 32'h04a43000;    //SUB R6, R5, R4
        processor.Mem[8] = 32'h18e73800;    //OR R7, R7, R7(Dummy Instruction)
        processor.Mem[9] = 32'h10c03800;   //SLT R7, R6, R0 (R7=0 if(R6>R0))
        processor.Mem[10] = 32'h19294800;   //OR R8, R8, R8(Dummy Instruction)
        processor.Mem[11] = 32'h48470002;   //SW R7, 2(R2)
        processor.Mem[12] = 32'h18e73800;   //OR R7, R7, R7(Dummy Instruction)
        processor.Mem[13] = 32'h44480002;   //LW R8, 2(R2)
        processor.Mem[14] = 32'h39200001;   //BEQ R9, R0, 2
        processor.Mem[15] = 32'h240c0003;   //ADDI 12, R0, 3
        processor.Mem[16] = 32'h240a000f;   //ADDI R10, R0, 15
        processor.Mem[17] = 32'hfc000000;   //HALT
        processor.HALTED = 0;
        processor.TAKEN_BRANCH = 0;
        processor.EX_MEM_BEQ_Cond = 0;
        processor.PC = 0;

        #500
        if(processor.Mem[22] == 0)
            $display("Positive Reg[12] = %2d", processor.Reg[12]);
        else
            $display("Negative Reg[12] = %2d", processor.Reg[12]);

        $finish;
    end
endmodule

main_tb.vcd
$date
	Sun Dec 24 01:00:07 2023
$end
$version
	Icarus Verilog
$end
$timescale
	100ps
$end
$scope module mips32_pipelined_tb1 $end
$var reg 1 ! clk1 $end
$var reg 1 " clk2 $end
$var integer 32 # k [31:0] $end
$scope module processor $end
$var wire 1 ! clk1 $end
$var wire 1 " clk2 $end
$var parameter 6 $ ADD $end
$var parameter 6 % ADDI $end
$var parameter 6 & AND $end
$var parameter 6 ' BEQ $end
$var parameter 3 ( BRANCH $end
$var parameter 6 ) DIV $end
$var parameter 6 * DIVI $end
$var parameter 3 + HALT $end
$var parameter 6 , HLT $end
$var parameter 3 - LOAD $end
$var parameter 6 . LW $end
$var parameter 6 / MUL $end
$var parameter 6 0 MULI $end
$var parameter 6 1 OR $end
$var parameter 3 2 RM_ALU $end
$var parameter 3 3 RR_ALU $end
$var parameter 6 4 SLL $end
$var parameter 6 5 SLT $end
$var parameter 6 6 SLTI $end
$var parameter 6 7 SRL $end
$var parameter 3 8 STORE $end
$var parameter 6 9 SUB $end
$var parameter 6 : SUBI $end
$var parameter 6 ; SW $end
$var reg 32 < EX_MEM_ALUOut [31:0] $end
$var reg 32 = EX_MEM_B [31:0] $end
$var reg 1 > EX_MEM_BEQ_Cond $end
$var reg 32 ? EX_MEM_IR [31:0] $end
$var reg 3 @ EX_MEM_TYPE [2:0] $end
$var reg 1 A HALTED $end
$var reg 32 B ID_EX_A [31:0] $end
$var reg 32 C ID_EX_B [31:0] $end
$var reg 32 D ID_EX_IR [31:0] $end
$var reg 32 E ID_EX_Imm [31:0] $end
$var reg 32 F ID_EX_NPC [31:0] $end
$var reg 3 G ID_EX_TYPE [2:0] $end
$var reg 32 H IF_ID_IR [31:0] $end
$var reg 32 I IF_ID_NPC [31:0] $end
$var reg 32 J MEM_WB_ALUOut [31:0] $end
$var reg 32 K MEM_WB_IR [31:0] $end
$var reg 32 L MEM_WB_LMD [31:0] $end
$var reg 3 M MEM_WB_TYPE [2:0] $end
$var reg 32 N PC [31:0] $end
$var reg 1 O TAKEN_BRANCH $end
$upscope $end
$upscope $end
$enddefinitions $end
$comment Show the parameter values. $end
$dumpall
b10010 ;
b1010 :
b1 9
b11 8
b1000 7
b1101 6
b100 5
b111 4
b0 3
b1 2
b110 1
b1011 0
b10 /
b10001 .
b10 -
b111111 ,
b111 +
b1100 *
b11 )
b100 (
b1110 '
b101 &
b1001 %
b0 $
$end
#0
$dumpvars
0O
b0 N
bx M
bx L
bx K
bx J
bx I
bx H
bx G
bx F
bx E
bx D
bx C
bx B
0A
bx @
bx ?
0>
bx =
bx <
b11111 #
0"
0!
$end
#50
1!
#70
b1 N
b1 I
b100100000000010000000000001010 H
#100
0!
#150
b0 B
1"
#170
b1010 E
b1 F
b100100000000010000000000001010 D
b1 G
b0 C
#200
0"
#250
1!
#270
b1010 <
b1 @
b100100000000010000000000001010 ?
b10 N
b10 I
b100100000000100000000000010100 H
#300
0!
#350
1"
#370
b1010 J
b100100000000010000000000001010 K
b1 M
b10100 E
b10 F
b100100000000100000000000010100 D
#400
0"
#450
1!
#470
b11 N
b11 I
b100100000000110000000000011110 H
b10100 <
b100100000000100000000000010100 ?
#500
0!
#550
1"
#570
b11110 E
b11 F
b100100000000110000000000011110 D
b10100 J
b100100000000100000000000010100 K
#600
0"
#650
1!
#670
b11110 <
b100100000000110000000000011110 ?
b100 N
b100 I
b11000111001110011100000000000 H
#700
0!
#750
1"
#770
b11110 J
b100100000000110000000000011110 K
b11100000000000 E
b100 F
b11000111001110011100000000000 D
b0 G
#800
0"
#850
1!
#870
b101 N
b101 I
b1000100010000000000000 H
b0 <
b0 @
b11000111001110011100000000000 ?
#900
0!
#950
1"
#970
b10000000000000 E
b101 F
b1000100010000000000000 D
b10100 C
b1010 B
b0 J
b11000111001110011100000000000 K
b0 M
#1000
0"
#1050
1!
#1070
b11110 <
b1000100010000000000000 ?
b110 N
b110 I
b10000110010100000000000 H
#1100
0!
#1150
1"
#1170
b11110 J
b1000100010000000000000 K
b10100000000000 E
b110 F
b10000110010100000000000 D
b11110 C
b10100 B
#1200
0"
#1250
1!
#1270
b111 N
b111 I
b11000111001110011100000000000 H
b110010 <
b10000110010100000000000 ?
#1300
0!
#1350
1"
#1370
b11100000000000 E
b111 F
b11000111001110011100000000000 D
b0 C
b0 B
b110010 J
b10000110010100000000000 K
#1400
0"
#1450
1!
#1470
b0 <
b11000111001110011100000000000 ?
b1000 N
b1000 I
b100101001000011000000000000 H
#1500
0!
#1550
1"
#1570
b0 J
b11000111001110011100000000000 K
b11000000000000 E
b1000 F
b100101001000011000000000000 D
b11110 C
b110010 B
#1600
0"
#1650
1!
#1670
b1001 N
b1001 I
b11000111001110011100000000000 H
b10100 <
b100101001000011000000000000 ?
#1700
0!
#1750
1"
#1770
b11100000000000 E
b1001 F
b11000111001110011100000000000 D
b0 C
b0 B
b10100 J
b100101001000011000000000000 K
#1800
0"
#1850
1!
#1870
b0 <
b11000111001110011100000000000 ?
b1010 N
b1010 I
b10000110000000011100000000000 H
#1900
0!
#1950
1"
#1970
b0 J
b11000111001110011100000000000 K
b1010 F
b10000110000000011100000000000 D
b10100 B
#2000
0"
#2050
1!
#2070
b1011 N
b1011 I
b11001001010010100100000000000 H
b10000110000000011100000000000 ?
#2100
0!
#2150
1"
#2170
b100100000000000 E
b1011 F
b11001001010010100100000000000 D
b0 B
b10000110000000011100000000000 K
#2200
0"
#2250
1!
#2270
b11001001010010100100000000000 ?
b1100 N
b1100 I
b1001000010001110000000000000010 H
#2300
0!
#2350
1"
#2370
b11001001010010100100000000000 K
b10 E
b1100 F
b1001000010001110000000000000010 D
b11 G
b10100 B
#2400
0"
#2450
1!
#2470
b1101 N
b1101 I
b11000111001110011100000000000 H
b0 =
b10110 <
b11 @
b1001000010001110000000000000010 ?
#2500
0!
#2550
1"
#2570
b11100000000000 E
b1101 F
b11000111001110011100000000000 D
b0 G
b0 B
b1001000010001110000000000000010 K
b11 M
#2600
0"
#2650
1!
#2670
b0 <
b0 @
b11000111001110011100000000000 ?
b1110 N
b1110 I
b1000100010010000000000000000010 H
#2700
0!
#2750
1"
#2770
b11000111001110011100000000000 K
b0 M
b10 E
b1110 F
b1000100010010000000000000000010 D
b10 G
b10100 B
#2800
0"
#2850
1!
#2870
b1111 N
b1111 I
b111001001000000000000000000001 H
b10110 <
b10 @
b1000100010010000000000000000010 ?
#2900
0!
#2950
1"
#2970
b1 E
b1111 F
b111001001000000000000000000001 D
b100 G
b0 B
b0 L
b1000100010010000000000000000010 K
b10 M
#3000
0"
#3050
1>
1!
#3070
b10000 <
b100 @
b111001001000000000000000000001 ?
b10000 N
b10000 I
b100100000011000000000000000011 H
#3100
0!
#3150
1"
#3170
b111001001000000000000000000001 K
b100 M
b11 E
b10000 F
b100100000011000000000000000011 D
b1 G
#3200
0"
#3250
1!
#3270
1O
b10001 N
b10001 I
b100100000010100000000000001111 H
b11 <
b1 @
b100100000011000000000000000011 ?
#3300
0!
#3350
1"
#3370
b1111 E
b10001 F
b100100000010100000000000001111 D
b11 J
b100100000011000000000000000011 K
b1 M
#3400
0"
#3450
1!
#3470
b1111 <
0O
b100100000010100000000000001111 ?
b10010 N
b10010 I
b11111100000000000000000000000000 H
#3500
0!
#3550
1"
#3570
b1111 J
b100100000010100000000000001111 K
b0 E
b10010 F
b11111100000000000000000000000000 D
b111 G
#3600
0"
#3650
1!
#3670
b10011 N
b10011 I
bx H
b111 @
b11111100000000000000000000000000 ?
#3700
0!
#3750
1"
#3770
bx E
b10011 F
bx D
bx C
bx B
b11111100000000000000000000000000 K
b111 M
#3800
0"
#3850
1!
#3870
1A
bx ?
b10100 N
b10100 I
